django_lionheart_helpers-3.0.4.dist-info/DESCRIPTION.rst
django_lionheart_helpers-3.0.4.dist-info/METADATA
django_lionheart_helpers-3.0.4.dist-info/RECORD
django_lionheart_helpers-3.0.4.dist-info/WHEEL
django_lionheart_helpers-3.0.4.dist-info/metadata.json
django_lionheart_helpers-3.0.4.dist-info/top_level.txt
lionheart/__init__.py
lionheart/admin.py
lionheart/decorators.py
lionheart/forms.py
lionheart/metadata.py
lionheart/models.py
lionheart/settings.py
lionheart/storages.py
lionheart/urls.py
lionheart/utils.py
lionheart/validators.py
lionheart/views.py
