Metadata-Version: 2.0
Name: django-lionheart-helpers
Version: 3.0.4
Summary: Django decorators and some other utilities.
Home-page: http://lionheartsw.com
Author: Dan Loewenherz
Author-email: dan@lionheartsw.com
License: Apache 2.0
Platform: UNKNOWN
